{"metadata": {"dbt_schema_version": "https://schemas.getdbt.com/dbt/run-results/v4.json", "dbt_version": "1.3.0", "generated_at": "2022-10-26T16:29:25.529869Z", "invocation_id": "9109541f-7fbc-46e5-9be0-ca4b706cbc1e", "env": {}}, "results": [{"status": "success", "timing": [{"name": "compile", "started_at": "2022-10-26T16:29:18.681724Z", "completed_at": "2022-10-26T16:29:18.686233Z"}, {"name": "execute", "started_at": "2022-10-26T16:29:18.686452Z", "completed_at": "2022-10-26T16:29:18.686471Z"}], "thread_id": "Thread-1", "execution_time": 0.0056688785552978516, "adapter_response": {}, "message": null, "failures": null, "unique_id": "model.asana_source.stg_asana__project_task_tmp"}, {"status": "success", "timing": [{"name": "compile", "started_at": "2022-10-26T16:29:18.687740Z", "completed_at": "2022-10-26T16:29:18.690995Z"}, {"name": "execute", "started_at": "2022-10-26T16:29:18.691180Z", "completed_at": "2022-10-26T16:29:18.691186Z"}], "thread_id": "Thread-1", "execution_time": 0.004192829132080078, "adapter_response": {}, "message": null, "failures": null, "unique_id": "model.asana_source.stg_asana__project_tmp"}, {"status": "success", "timing": [{"name": "compile", "started_at": "2022-10-26T16:29:18.692419Z", "completed_at": "2022-10-26T16:29:18.697660Z"}, {"name": "execute", "started_at": "2022-10-26T16:29:18.697883Z", "completed_at": "2022-10-26T16:29:18.697889Z"}], "thread_id": "Thread-1", "execution_time": 0.006258964538574219, "adapter_response": {}, "message": null, "failures": null, "unique_id": "model.asana_source.stg_asana__section_tmp"}, {"status": "success", "timing": [{"name": "compile", "started_at": "2022-10-26T16:29:18.699151Z", "completed_at": "2022-10-26T16:29:18.703982Z"}, {"name": "execute", "started_at": "2022-10-26T16:29:18.704147Z", "completed_at": "2022-10-26T16:29:18.704154Z"}], "thread_id": "Thread-1", "execution_time": 0.005769252777099609, "adapter_response": {}, "message": null, "failures": null, "unique_id": "model.asana_source.stg_asana__story_tmp"}, {"status": "success", "timing": [{"name": "compile", "started_at": "2022-10-26T16:29:18.705335Z", "completed_at": "2022-10-26T16:29:18.708426Z"}, {"name": "execute", "started_at": "2022-10-26T16:29:18.708600Z", "completed_at": "2022-10-26T16:29:18.708606Z"}], "thread_id": "Thread-1", "execution_time": 0.004117012023925781, "adapter_response": {}, "message": null, "failures": null, "unique_id": "model.asana_source.stg_asana__tag_tmp"}, {"status": "success", "timing": [{"name": "compile", "started_at": "2022-10-26T16:29:18.709624Z", "completed_at": "2022-10-26T16:29:18.712090Z"}, {"name": "execute", "started_at": "2022-10-26T16:29:18.712242Z", "completed_at": "2022-10-26T16:29:18.712247Z"}], "thread_id": "Thread-1", "execution_time": 0.0032720565795898438, "adapter_response": {}, "message": null, "failures": null, "unique_id": "model.asana_source.stg_asana__task_follower_tmp"}, {"status": "success", "timing": [{"name": "compile", "started_at": "2022-10-26T16:29:18.713101Z", "completed_at": "2022-10-26T16:29:18.716136Z"}, {"name": "execute", "started_at": "2022-10-26T16:29:18.716305Z", "completed_at": "2022-10-26T16:29:18.716311Z"}], "thread_id": "Thread-1", "execution_time": 0.0038640499114990234, "adapter_response": {}, "message": null, "failures": null, "unique_id": "model.asana_source.stg_asana__task_section_tmp"}, {"status": "success", "timing": [{"name": "compile", "started_at": "2022-10-26T16:29:18.717373Z", "completed_at": "2022-10-26T16:29:18.720240Z"}, {"name": "execute", "started_at": "2022-10-26T16:29:18.720395Z", "completed_at": "2022-10-26T16:29:18.720401Z"}], "thread_id": "Thread-1", "execution_time": 0.0036928653717041016, "adapter_response": {}, "message": null, "failures": null, "unique_id": "model.asana_source.stg_asana__task_tag_tmp"}, {"status": "success", "timing": [{"name": "compile", "started_at": "2022-10-26T16:29:18.721458Z", "completed_at": "2022-10-26T16:29:18.724614Z"}, {"name": "execute", "started_at": "2022-10-26T16:29:18.724758Z", "completed_at": "2022-10-26T16:29:18.724762Z"}], "thread_id": "Thread-1", "execution_time": 0.0039920806884765625, "adapter_response": {}, "message": null, "failures": null, "unique_id": "model.asana_source.stg_asana__task_tmp"}, {"status": "success", "timing": [{"name": "compile", "started_at": "2022-10-26T16:29:18.725562Z", "completed_at": "2022-10-26T16:29:18.728240Z"}, {"name": "execute", "started_at": "2022-10-26T16:29:18.728393Z", "completed_at": "2022-10-26T16:29:18.728398Z"}], "thread_id": "Thread-1", "execution_time": 0.0033550262451171875, "adapter_response": {}, "message": null, "failures": null, "unique_id": "model.asana_source.stg_asana__team_tmp"}, {"status": "success", "timing": [{"name": "compile", "started_at": "2022-10-26T16:29:18.729351Z", "completed_at": "2022-10-26T16:29:18.731986Z"}, {"name": "execute", "started_at": "2022-10-26T16:29:18.732127Z", "completed_at": "2022-10-26T16:29:18.732133Z"}], "thread_id": "Thread-1", "execution_time": 0.0034329891204833984, "adapter_response": {}, "message": null, "failures": null, "unique_id": "model.asana_source.stg_asana__user_tmp"}, {"status": "success", "timing": [{"name": "compile", "started_at": "2022-10-26T16:29:18.733052Z", "completed_at": "2022-10-26T16:29:18.734332Z"}, {"name": "execute", "started_at": "2022-10-26T16:29:18.734452Z", "completed_at": "2022-10-26T16:29:18.734455Z"}], "thread_id": "Thread-1", "execution_time": 0.001965045928955078, "adapter_response": {}, "message": null, "failures": null, "unique_id": "seed.asana_integration_tests.project_data"}, {"status": "success", "timing": [{"name": "compile", "started_at": "2022-10-26T16:29:18.735128Z", "completed_at": "2022-10-26T16:29:18.736218Z"}, {"name": "execute", "started_at": "2022-10-26T16:29:18.736333Z", "completed_at": "2022-10-26T16:29:18.736336Z"}], "thread_id": "Thread-1", "execution_time": 0.0016460418701171875, "adapter_response": {}, "message": null, "failures": null, "unique_id": "seed.asana_integration_tests.project_task_data"}, {"status": "success", "timing": [{"name": "compile", "started_at": "2022-10-26T16:29:18.736970Z", "completed_at": "2022-10-26T16:29:18.738173Z"}, {"name": "execute", "started_at": "2022-10-26T16:29:18.738312Z", "completed_at": "2022-10-26T16:29:18.738316Z"}], "thread_id": "Thread-1", "execution_time": 0.001825094223022461, "adapter_response": {}, "message": null, "failures": null, "unique_id": "seed.asana_integration_tests.section_data"}, {"status": "success", "timing": [{"name": "compile", "started_at": "2022-10-26T16:29:18.739045Z", "completed_at": "2022-10-26T16:29:18.740943Z"}, {"name": "execute", "started_at": "2022-10-26T16:29:18.741110Z", "completed_at": "2022-10-26T16:29:18.741114Z"}], "thread_id": "Thread-1", "execution_time": 0.0025610923767089844, "adapter_response": {}, "message": null, "failures": null, "unique_id": "seed.asana_integration_tests.story_data"}, {"status": "success", "timing": [{"name": "compile", "started_at": "2022-10-26T16:29:18.741980Z", "completed_at": "2022-10-26T16:29:18.743184Z"}, {"name": "execute", "started_at": "2022-10-26T16:29:18.743300Z", "completed_at": "2022-10-26T16:29:18.743304Z"}], "thread_id": "Thread-1", "execution_time": 0.0019178390502929688, "adapter_response": {}, "message": null, "failures": null, "unique_id": "seed.asana_integration_tests.tag_data"}, {"status": "success", "timing": [{"name": "compile", "started_at": "2022-10-26T16:29:18.744101Z", "completed_at": "2022-10-26T16:29:18.745505Z"}, {"name": "execute", "started_at": "2022-10-26T16:29:18.745643Z", "completed_at": "2022-10-26T16:29:18.745648Z"}], "thread_id": "Thread-1", "execution_time": 0.0021169185638427734, "adapter_response": {}, "message": null, "failures": null, "unique_id": "seed.asana_integration_tests.task_data"}, {"status": "success", "timing": [{"name": "compile", "started_at": "2022-10-26T16:29:18.746375Z", "completed_at": "2022-10-26T16:29:18.747462Z"}, {"name": "execute", "started_at": "2022-10-26T16:29:18.747590Z", "completed_at": "2022-10-26T16:29:18.747593Z"}], "thread_id": "Thread-1", "execution_time": 0.0017278194427490234, "adapter_response": {}, "message": null, "failures": null, "unique_id": "seed.asana_integration_tests.task_follower_data"}, {"status": "success", "timing": [{"name": "compile", "started_at": "2022-10-26T16:29:18.748342Z", "completed_at": "2022-10-26T16:29:18.749541Z"}, {"name": "execute", "started_at": "2022-10-26T16:29:18.749654Z", "completed_at": "2022-10-26T16:29:18.749657Z"}], "thread_id": "Thread-1", "execution_time": 0.0018320083618164062, "adapter_response": {}, "message": null, "failures": null, "unique_id": "seed.asana_integration_tests.task_section_data"}, {"status": "success", "timing": [{"name": "compile", "started_at": "2022-10-26T16:29:18.750286Z", "completed_at": "2022-10-26T16:29:18.752199Z"}, {"name": "execute", "started_at": "2022-10-26T16:29:18.752334Z", "completed_at": "2022-10-26T16:29:18.752338Z"}], "thread_id": "Thread-1", "execution_time": 0.002530813217163086, "adapter_response": {}, "message": null, "failures": null, "unique_id": "seed.asana_integration_tests.task_tag_data"}, {"status": "success", "timing": [{"name": "compile", "started_at": "2022-10-26T16:29:18.753085Z", "completed_at": "2022-10-26T16:29:18.754350Z"}, {"name": "execute", "started_at": "2022-10-26T16:29:18.754502Z", "completed_at": "2022-10-26T16:29:18.754506Z"}], "thread_id": "Thread-1", "execution_time": 0.0019159317016601562, "adapter_response": {}, "message": null, "failures": null, "unique_id": "seed.asana_integration_tests.team_data"}, {"status": "success", "timing": [{"name": "compile", "started_at": "2022-10-26T16:29:18.755382Z", "completed_at": "2022-10-26T16:29:18.756744Z"}, {"name": "execute", "started_at": "2022-10-26T16:29:18.756879Z", "completed_at": "2022-10-26T16:29:18.756883Z"}], "thread_id": "Thread-1", "execution_time": 0.0021429061889648438, "adapter_response": {}, "message": null, "failures": null, "unique_id": "seed.asana_integration_tests.user_data"}, {"status": "success", "timing": [{"name": "compile", "started_at": "2022-10-26T16:29:18.757587Z", "completed_at": "2022-10-26T16:29:19.174223Z"}, {"name": "execute", "started_at": "2022-10-26T16:29:19.174547Z", "completed_at": "2022-10-26T16:29:19.174569Z"}], "thread_id": "Thread-1", "execution_time": 0.41772890090942383, "adapter_response": {}, "message": null, "failures": null, "unique_id": "model.asana_source.stg_asana__project_task"}, {"status": "success", "timing": [{"name": "compile", "started_at": "2022-10-26T16:29:19.176372Z", "completed_at": "2022-10-26T16:29:19.648490Z"}, {"name": "execute", "started_at": "2022-10-26T16:29:19.648789Z", "completed_at": "2022-10-26T16:29:19.648800Z"}], "thread_id": "Thread-1", "execution_time": 0.4735710620880127, "adapter_response": {}, "message": null, "failures": null, "unique_id": "model.asana_source.stg_asana__project"}, {"status": "success", "timing": [{"name": "compile", "started_at": "2022-10-26T16:29:19.650603Z", "completed_at": "2022-10-26T16:29:20.033262Z"}, {"name": "execute", "started_at": "2022-10-26T16:29:20.033848Z", "completed_at": "2022-10-26T16:29:20.033863Z"}], "thread_id": "Thread-1", "execution_time": 0.3845796585083008, "adapter_response": {}, "message": null, "failures": null, "unique_id": "model.asana_source.stg_asana__section"}, {"status": "success", "timing": [{"name": "compile", "started_at": "2022-10-26T16:29:20.036103Z", "completed_at": "2022-10-26T16:29:20.355003Z"}, {"name": "execute", "started_at": "2022-10-26T16:29:20.355283Z", "completed_at": "2022-10-26T16:29:20.355292Z"}], "thread_id": "Thread-1", "execution_time": 0.32041311264038086, "adapter_response": {}, "message": null, "failures": null, "unique_id": "model.asana_source.stg_asana__story"}, {"status": "success", "timing": [{"name": "compile", "started_at": "2022-10-26T16:29:20.356685Z", "completed_at": "2022-10-26T16:29:20.685720Z"}, {"name": "execute", "started_at": "2022-10-26T16:29:20.686072Z", "completed_at": "2022-10-26T16:29:20.686092Z"}], "thread_id": "Thread-1", "execution_time": 0.33046507835388184, "adapter_response": {}, "message": null, "failures": null, "unique_id": "model.asana_source.stg_asana__tag"}, {"status": "success", "timing": [{"name": "compile", "started_at": "2022-10-26T16:29:20.688074Z", "completed_at": "2022-10-26T16:29:21.041287Z"}, {"name": "execute", "started_at": "2022-10-26T16:29:21.041636Z", "completed_at": "2022-10-26T16:29:21.041653Z"}], "thread_id": "Thread-1", "execution_time": 0.35494184494018555, "adapter_response": {}, "message": null, "failures": null, "unique_id": "model.asana_source.stg_asana__task_follower"}, {"status": "success", "timing": [{"name": "compile", "started_at": "2022-10-26T16:29:21.043606Z", "completed_at": "2022-10-26T16:29:21.443710Z"}, {"name": "execute", "started_at": "2022-10-26T16:29:21.444029Z", "completed_at": "2022-10-26T16:29:21.444046Z"}], "thread_id": "Thread-1", "execution_time": 0.40150022506713867, "adapter_response": {}, "message": null, "failures": null, "unique_id": "model.asana_source.stg_asana__task_section"}, {"status": "success", "timing": [{"name": "compile", "started_at": "2022-10-26T16:29:21.445715Z", "completed_at": "2022-10-26T16:29:21.751489Z"}, {"name": "execute", "started_at": "2022-10-26T16:29:21.751872Z", "completed_at": "2022-10-26T16:29:21.751890Z"}], "thread_id": "Thread-1", "execution_time": 0.30763983726501465, "adapter_response": {}, "message": null, "failures": null, "unique_id": "model.asana_source.stg_asana__task_tag"}, {"status": "success", "timing": [{"name": "compile", "started_at": "2022-10-26T16:29:21.754930Z", "completed_at": "2022-10-26T16:29:22.140745Z"}, {"name": "execute", "started_at": "2022-10-26T16:29:22.141052Z", "completed_at": "2022-10-26T16:29:22.141068Z"}], "thread_id": "Thread-1", "execution_time": 0.38755297660827637, "adapter_response": {}, "message": null, "failures": null, "unique_id": "model.asana_source.stg_asana__task"}, {"status": "success", "timing": [{"name": "compile", "started_at": "2022-10-26T16:29:22.142809Z", "completed_at": "2022-10-26T16:29:22.508619Z"}, {"name": "execute", "started_at": "2022-10-26T16:29:22.508866Z", "completed_at": "2022-10-26T16:29:22.508874Z"}], "thread_id": "Thread-1", "execution_time": 0.36721205711364746, "adapter_response": {}, "message": null, "failures": null, "unique_id": "model.asana_source.stg_asana__team"}, {"status": "success", "timing": [{"name": "compile", "started_at": "2022-10-26T16:29:22.510227Z", "completed_at": "2022-10-26T16:29:22.803400Z"}, {"name": "execute", "started_at": "2022-10-26T16:29:22.803746Z", "completed_at": "2022-10-26T16:29:22.803764Z"}], "thread_id": "Thread-1", "execution_time": 0.2946197986602783, "adapter_response": {}, "message": null, "failures": null, "unique_id": "model.asana_source.stg_asana__user"}, {"status": "success", "timing": [{"name": "compile", "started_at": "2022-10-26T16:29:22.805703Z", "completed_at": "2022-10-26T16:29:22.817854Z"}, {"name": "execute", "started_at": "2022-10-26T16:29:22.818071Z", "completed_at": "2022-10-26T16:29:22.818077Z"}], "thread_id": "Thread-1", "execution_time": 0.013281822204589844, "adapter_response": {}, "message": null, "failures": null, "unique_id": "test.asana_source.not_null_stg_asana__project_task_project_id.e2450d16b1"}, {"status": "success", "timing": [{"name": "compile", "started_at": "2022-10-26T16:29:22.819165Z", "completed_at": "2022-10-26T16:29:22.823000Z"}, {"name": "execute", "started_at": "2022-10-26T16:29:22.823184Z", "completed_at": "2022-10-26T16:29:22.823189Z"}], "thread_id": "Thread-1", "execution_time": 0.0047512054443359375, "adapter_response": {}, "message": null, "failures": null, "unique_id": "test.asana_source.not_null_stg_asana__project_task_task_id.9479566014"}, {"status": "success", "timing": [{"name": "compile", "started_at": "2022-10-26T16:29:22.824265Z", "completed_at": "2022-10-26T16:29:22.831268Z"}, {"name": "execute", "started_at": "2022-10-26T16:29:22.831443Z", "completed_at": "2022-10-26T16:29:22.831449Z"}], "thread_id": "Thread-1", "execution_time": 0.007896900177001953, "adapter_response": {}, "message": null, "failures": null, "unique_id": "test.asana_source.not_null_stg_asana__project_project_id.d27dae84fa"}, {"status": "success", "timing": [{"name": "compile", "started_at": "2022-10-26T16:29:22.832339Z", "completed_at": "2022-10-26T16:29:22.837279Z"}, {"name": "execute", "started_at": "2022-10-26T16:29:22.837459Z", "completed_at": "2022-10-26T16:29:22.837465Z"}], "thread_id": "Thread-1", "execution_time": 0.0057299137115478516, "adapter_response": {}, "message": null, "failures": null, "unique_id": "test.asana_source.unique_stg_asana__project_project_id.67bfab1228"}, {"status": "success", "timing": [{"name": "compile", "started_at": "2022-10-26T16:29:22.838454Z", "completed_at": "2022-10-26T16:29:22.841648Z"}, {"name": "execute", "started_at": "2022-10-26T16:29:22.841809Z", "completed_at": "2022-10-26T16:29:22.841814Z"}], "thread_id": "Thread-1", "execution_time": 0.003984212875366211, "adapter_response": {}, "message": null, "failures": null, "unique_id": "test.asana_source.not_null_stg_asana__section_section_id.389ebce958"}, {"status": "success", "timing": [{"name": "compile", "started_at": "2022-10-26T16:29:22.842701Z", "completed_at": "2022-10-26T16:29:22.845769Z"}, {"name": "execute", "started_at": "2022-10-26T16:29:22.845931Z", "completed_at": "2022-10-26T16:29:22.845936Z"}], "thread_id": "Thread-1", "execution_time": 0.003832101821899414, "adapter_response": {}, "message": null, "failures": null, "unique_id": "test.asana_source.unique_stg_asana__section_section_id.0495dd3d2f"}, {"status": "success", "timing": [{"name": "compile", "started_at": "2022-10-26T16:29:22.846766Z", "completed_at": "2022-10-26T16:29:22.849857Z"}, {"name": "execute", "started_at": "2022-10-26T16:29:22.850009Z", "completed_at": "2022-10-26T16:29:22.850014Z"}], "thread_id": "Thread-1", "execution_time": 0.0037958621978759766, "adapter_response": {}, "message": null, "failures": null, "unique_id": "test.asana_source.not_null_stg_asana__story_story_id.ca847d0848"}, {"status": "success", "timing": [{"name": "compile", "started_at": "2022-10-26T16:29:22.850828Z", "completed_at": "2022-10-26T16:29:22.854506Z"}, {"name": "execute", "started_at": "2022-10-26T16:29:22.854653Z", "completed_at": "2022-10-26T16:29:22.854657Z"}], "thread_id": "Thread-1", "execution_time": 0.004373073577880859, "adapter_response": {}, "message": null, "failures": null, "unique_id": "test.asana_source.not_null_stg_asana__story_target_task_id.3f971de06e"}, {"status": "success", "timing": [{"name": "compile", "started_at": "2022-10-26T16:29:22.855393Z", "completed_at": "2022-10-26T16:29:22.858131Z"}, {"name": "execute", "started_at": "2022-10-26T16:29:22.858270Z", "completed_at": "2022-10-26T16:29:22.858274Z"}], "thread_id": "Thread-1", "execution_time": 0.003368377685546875, "adapter_response": {}, "message": null, "failures": null, "unique_id": "test.asana_source.unique_stg_asana__story_story_id.414f25bb84"}, {"status": "success", "timing": [{"name": "compile", "started_at": "2022-10-26T16:29:22.858978Z", "completed_at": "2022-10-26T16:29:22.861662Z"}, {"name": "execute", "started_at": "2022-10-26T16:29:22.861804Z", "completed_at": "2022-10-26T16:29:22.861808Z"}], "thread_id": "Thread-1", "execution_time": 0.0033080577850341797, "adapter_response": {}, "message": null, "failures": null, "unique_id": "test.asana_source.not_null_stg_asana__tag_tag_id.c6a8187ca2"}, {"status": "success", "timing": [{"name": "compile", "started_at": "2022-10-26T16:29:22.862537Z", "completed_at": "2022-10-26T16:29:22.865415Z"}, {"name": "execute", "started_at": "2022-10-26T16:29:22.865562Z", "completed_at": "2022-10-26T16:29:22.865567Z"}], "thread_id": "Thread-1", "execution_time": 0.003506183624267578, "adapter_response": {}, "message": null, "failures": null, "unique_id": "test.asana_source.unique_stg_asana__tag_tag_id.fd78b190c7"}, {"status": "success", "timing": [{"name": "compile", "started_at": "2022-10-26T16:29:22.866296Z", "completed_at": "2022-10-26T16:29:22.868998Z"}, {"name": "execute", "started_at": "2022-10-26T16:29:22.869135Z", "completed_at": "2022-10-26T16:29:22.869139Z"}], "thread_id": "Thread-1", "execution_time": 0.003323793411254883, "adapter_response": {}, "message": null, "failures": null, "unique_id": "test.asana_source.not_null_stg_asana__task_follower_task_id.5af35f322c"}, {"status": "success", "timing": [{"name": "compile", "started_at": "2022-10-26T16:29:22.869860Z", "completed_at": "2022-10-26T16:29:22.873095Z"}, {"name": "execute", "started_at": "2022-10-26T16:29:22.873228Z", "completed_at": "2022-10-26T16:29:22.873232Z"}], "thread_id": "Thread-1", "execution_time": 0.0038390159606933594, "adapter_response": {}, "message": null, "failures": null, "unique_id": "test.asana_source.not_null_stg_asana__task_follower_user_id.e0aea0b15e"}, {"status": "success", "timing": [{"name": "compile", "started_at": "2022-10-26T16:29:22.880285Z", "completed_at": "2022-10-26T16:29:22.883171Z"}, {"name": "execute", "started_at": "2022-10-26T16:29:22.883310Z", "completed_at": "2022-10-26T16:29:22.883315Z"}], "thread_id": "Thread-1", "execution_time": 0.0035948753356933594, "adapter_response": {}, "message": null, "failures": null, "unique_id": "test.asana_source.not_null_stg_asana__task_section_section_id.b0977a4cfe"}, {"status": "success", "timing": [{"name": "compile", "started_at": "2022-10-26T16:29:22.884105Z", "completed_at": "2022-10-26T16:29:22.886850Z"}, {"name": "execute", "started_at": "2022-10-26T16:29:22.886992Z", "completed_at": "2022-10-26T16:29:22.886996Z"}], "thread_id": "Thread-1", "execution_time": 0.003451108932495117, "adapter_response": {}, "message": null, "failures": null, "unique_id": "test.asana_source.not_null_stg_asana__task_section_task_id.ab81301de8"}, {"status": "success", "timing": [{"name": "compile", "started_at": "2022-10-26T16:29:22.891803Z", "completed_at": "2022-10-26T16:29:22.895190Z"}, {"name": "execute", "started_at": "2022-10-26T16:29:22.895328Z", "completed_at": "2022-10-26T16:29:22.895332Z"}], "thread_id": "Thread-1", "execution_time": 0.004015207290649414, "adapter_response": {}, "message": null, "failures": null, "unique_id": "test.asana_source.not_null_stg_asana__task_tag_tag_id.d523de41d8"}, {"status": "success", "timing": [{"name": "compile", "started_at": "2022-10-26T16:29:22.896018Z", "completed_at": "2022-10-26T16:29:22.898541Z"}, {"name": "execute", "started_at": "2022-10-26T16:29:22.898684Z", "completed_at": "2022-10-26T16:29:22.898688Z"}], "thread_id": "Thread-1", "execution_time": 0.0031380653381347656, "adapter_response": {}, "message": null, "failures": null, "unique_id": "test.asana_source.not_null_stg_asana__task_tag_task_id.9d27624748"}, {"status": "success", "timing": [{"name": "compile", "started_at": "2022-10-26T16:29:22.899357Z", "completed_at": "2022-10-26T16:29:22.902000Z"}, {"name": "execute", "started_at": "2022-10-26T16:29:22.902137Z", "completed_at": "2022-10-26T16:29:22.902142Z"}], "thread_id": "Thread-1", "execution_time": 0.0032510757446289062, "adapter_response": {}, "message": null, "failures": null, "unique_id": "test.asana_source.not_null_stg_asana__task_task_id.924cc69000"}, {"status": "success", "timing": [{"name": "compile", "started_at": "2022-10-26T16:29:22.902828Z", "completed_at": "2022-10-26T16:29:22.905280Z"}, {"name": "execute", "started_at": "2022-10-26T16:29:22.905408Z", "completed_at": "2022-10-26T16:29:22.905412Z"}], "thread_id": "Thread-1", "execution_time": 0.00304412841796875, "adapter_response": {}, "message": null, "failures": null, "unique_id": "test.asana_source.unique_stg_asana__task_task_id.a5271275a5"}, {"status": "success", "timing": [{"name": "compile", "started_at": "2022-10-26T16:29:22.906082Z", "completed_at": "2022-10-26T16:29:22.908645Z"}, {"name": "execute", "started_at": "2022-10-26T16:29:22.908772Z", "completed_at": "2022-10-26T16:29:22.908776Z"}], "thread_id": "Thread-1", "execution_time": 0.0031838417053222656, "adapter_response": {}, "message": null, "failures": null, "unique_id": "test.asana_source.not_null_stg_asana__team_team_id.e12b563474"}, {"status": "success", "timing": [{"name": "compile", "started_at": "2022-10-26T16:29:22.909444Z", "completed_at": "2022-10-26T16:29:22.911886Z"}, {"name": "execute", "started_at": "2022-10-26T16:29:22.912021Z", "completed_at": "2022-10-26T16:29:22.912025Z"}], "thread_id": "Thread-1", "execution_time": 0.0030341148376464844, "adapter_response": {}, "message": null, "failures": null, "unique_id": "test.asana_source.unique_stg_asana__team_team_id.111fe15873"}, {"status": "success", "timing": [{"name": "compile", "started_at": "2022-10-26T16:29:22.926372Z", "completed_at": "2022-10-26T16:29:22.929181Z"}, {"name": "execute", "started_at": "2022-10-26T16:29:22.929330Z", "completed_at": "2022-10-26T16:29:22.929334Z"}], "thread_id": "Thread-1", "execution_time": 0.0034618377685546875, "adapter_response": {}, "message": null, "failures": null, "unique_id": "test.asana_source.not_null_stg_asana__user_user_id.4e900e8ec6"}, {"status": "success", "timing": [{"name": "compile", "started_at": "2022-10-26T16:29:22.930147Z", "completed_at": "2022-10-26T16:29:22.932998Z"}, {"name": "execute", "started_at": "2022-10-26T16:29:22.933132Z", "completed_at": "2022-10-26T16:29:22.933136Z"}], "thread_id": "Thread-1", "execution_time": 0.0035200119018554688, "adapter_response": {}, "message": null, "failures": null, "unique_id": "test.asana_source.unique_stg_asana__user_user_id.73808d6267"}, {"status": "success", "timing": [{"name": "compile", "started_at": "2022-10-26T16:29:22.933861Z", "completed_at": "2022-10-26T16:29:22.941460Z"}, {"name": "execute", "started_at": "2022-10-26T16:29:22.941613Z", "completed_at": "2022-10-26T16:29:22.941618Z"}], "thread_id": "Thread-1", "execution_time": 0.008272886276245117, "adapter_response": {}, "message": null, "failures": null, "unique_id": "test.asana.not_null_int_asana__task_projects_task_id.322519ee10"}, {"status": "success", "timing": [{"name": "compile", "started_at": "2022-10-26T16:29:22.942361Z", "completed_at": "2022-10-26T16:29:22.946806Z"}, {"name": "execute", "started_at": "2022-10-26T16:29:22.946945Z", "completed_at": "2022-10-26T16:29:22.946950Z"}], "thread_id": "Thread-1", "execution_time": 0.005059003829956055, "adapter_response": {}, "message": null, "failures": null, "unique_id": "test.asana.unique_int_asana__task_projects_task_id.8a6b2f262d"}, {"status": "success", "timing": [{"name": "compile", "started_at": "2022-10-26T16:29:22.947625Z", "completed_at": "2022-10-26T16:29:22.950951Z"}, {"name": "execute", "started_at": "2022-10-26T16:29:22.951082Z", "completed_at": "2022-10-26T16:29:22.951086Z"}], "thread_id": "Thread-1", "execution_time": 0.0039250850677490234, "adapter_response": {}, "message": null, "failures": null, "unique_id": "test.asana.not_null_int_asana__task_tags_task_id.34eec2b834"}, {"status": "success", "timing": [{"name": "compile", "started_at": "2022-10-26T16:29:22.951748Z", "completed_at": "2022-10-26T16:29:22.956326Z"}, {"name": "execute", "started_at": "2022-10-26T16:29:22.956474Z", "completed_at": "2022-10-26T16:29:22.956479Z"}], "thread_id": "Thread-1", "execution_time": 0.005235910415649414, "adapter_response": {}, "message": null, "failures": null, "unique_id": "test.asana.unique_int_asana__task_tags_task_id.f28aff2685"}, {"status": "success", "timing": [{"name": "compile", "started_at": "2022-10-26T16:29:22.979479Z", "completed_at": "2022-10-26T16:29:22.983181Z"}, {"name": "execute", "started_at": "2022-10-26T16:29:22.983322Z", "completed_at": "2022-10-26T16:29:22.983328Z"}], "thread_id": "Thread-1", "execution_time": 0.004346132278442383, "adapter_response": {}, "message": null, "failures": null, "unique_id": "test.asana.not_null_int_asana__task_assignee_task_id.a9c81bd443"}, {"status": "success", "timing": [{"name": "compile", "started_at": "2022-10-26T16:29:22.984038Z", "completed_at": "2022-10-26T16:29:22.988244Z"}, {"name": "execute", "started_at": "2022-10-26T16:29:22.988377Z", "completed_at": "2022-10-26T16:29:22.988382Z"}], "thread_id": "Thread-1", "execution_time": 0.0048258304595947266, "adapter_response": {}, "message": null, "failures": null, "unique_id": "test.asana.unique_int_asana__task_assignee_task_id.b4e2ea04e1"}, {"status": "success", "timing": [{"name": "compile", "started_at": "2022-10-26T16:29:22.989054Z", "completed_at": "2022-10-26T16:29:22.992447Z"}, {"name": "execute", "started_at": "2022-10-26T16:29:22.992581Z", "completed_at": "2022-10-26T16:29:22.992584Z"}], "thread_id": "Thread-1", "execution_time": 0.003997087478637695, "adapter_response": {}, "message": null, "failures": null, "unique_id": "test.asana.not_null_int_asana__task_followers_task_id.6791bf2573"}, {"status": "success", "timing": [{"name": "compile", "started_at": "2022-10-26T16:29:22.993276Z", "completed_at": "2022-10-26T16:29:22.998257Z"}, {"name": "execute", "started_at": "2022-10-26T16:29:22.998404Z", "completed_at": "2022-10-26T16:29:22.998408Z"}], "thread_id": "Thread-1", "execution_time": 0.0056056976318359375, "adapter_response": {}, "message": null, "failures": null, "unique_id": "test.asana.unique_int_asana__task_followers_task_id.eeb3667df9"}, {"status": "success", "timing": [{"name": "compile", "started_at": "2022-10-26T16:29:23.026811Z", "completed_at": "2022-10-26T16:29:23.031420Z"}, {"name": "execute", "started_at": "2022-10-26T16:29:23.031556Z", "completed_at": "2022-10-26T16:29:23.031561Z"}], "thread_id": "Thread-1", "execution_time": 0.005221843719482422, "adapter_response": {}, "message": null, "failures": null, "unique_id": "test.asana.not_null_int_asana__task_story_story_id.1ffdb99927"}, {"status": "success", "timing": [{"name": "compile", "started_at": "2022-10-26T16:29:23.032311Z", "completed_at": "2022-10-26T16:29:23.036739Z"}, {"name": "execute", "started_at": "2022-10-26T16:29:23.036898Z", "completed_at": "2022-10-26T16:29:23.036903Z"}], "thread_id": "Thread-1", "execution_time": 0.005123138427734375, "adapter_response": {}, "message": null, "failures": null, "unique_id": "test.asana.unique_int_asana__task_story_story_id.92d7adbcf6"}, {"status": "success", "timing": [{"name": "compile", "started_at": "2022-10-26T16:29:23.037812Z", "completed_at": "2022-10-26T16:29:23.046351Z"}, {"name": "execute", "started_at": "2022-10-26T16:29:23.046502Z", "completed_at": "2022-10-26T16:29:23.046507Z"}], "thread_id": "Thread-1", "execution_time": 0.00931692123413086, "adapter_response": {}, "message": null, "failures": null, "unique_id": "test.asana.dbt_utils_unique_combination_of_columns_int_asana__project_user_project_id__user_id__role__currently_working_on.f9493098e0"}, {"status": "success", "timing": [{"name": "compile", "started_at": "2022-10-26T16:29:23.047260Z", "completed_at": "2022-10-26T16:29:23.050810Z"}, {"name": "execute", "started_at": "2022-10-26T16:29:23.050945Z", "completed_at": "2022-10-26T16:29:23.050949Z"}], "thread_id": "Thread-1", "execution_time": 0.004173994064331055, "adapter_response": {}, "message": null, "failures": null, "unique_id": "test.asana.not_null_int_asana__subtask_parent_subtask_id.024565c768"}, {"status": "success", "timing": [{"name": "compile", "started_at": "2022-10-26T16:29:23.051638Z", "completed_at": "2022-10-26T16:29:23.055919Z"}, {"name": "execute", "started_at": "2022-10-26T16:29:23.056056Z", "completed_at": "2022-10-26T16:29:23.056061Z"}], "thread_id": "Thread-1", "execution_time": 0.0048999786376953125, "adapter_response": {}, "message": null, "failures": null, "unique_id": "test.asana.unique_int_asana__subtask_parent_subtask_id.641dfb3c8f"}, {"status": "success", "timing": [{"name": "compile", "started_at": "2022-10-26T16:29:23.056737Z", "completed_at": "2022-10-26T16:29:23.060795Z"}, {"name": "execute", "started_at": "2022-10-26T16:29:23.060933Z", "completed_at": "2022-10-26T16:29:23.060937Z"}], "thread_id": "Thread-1", "execution_time": 0.0046808719635009766, "adapter_response": {}, "message": null, "failures": null, "unique_id": "test.asana.not_null_int_asana__task_comments_task_id.6986f1d77f"}, {"status": "success", "timing": [{"name": "compile", "started_at": "2022-10-26T16:29:23.061677Z", "completed_at": "2022-10-26T16:29:23.065989Z"}, {"name": "execute", "started_at": "2022-10-26T16:29:23.066124Z", "completed_at": "2022-10-26T16:29:23.066128Z"}], "thread_id": "Thread-1", "execution_time": 0.00494694709777832, "adapter_response": {}, "message": null, "failures": null, "unique_id": "test.asana.unique_int_asana__task_comments_task_id.f012fa6a04"}, {"status": "success", "timing": [{"name": "compile", "started_at": "2022-10-26T16:29:23.066790Z", "completed_at": "2022-10-26T16:29:23.070175Z"}, {"name": "execute", "started_at": "2022-10-26T16:29:23.070306Z", "completed_at": "2022-10-26T16:29:23.070310Z"}], "thread_id": "Thread-1", "execution_time": 0.00397801399230957, "adapter_response": {}, "message": null, "failures": null, "unique_id": "test.asana.not_null_int_asana__task_first_modifier_task_id.495738ff52"}, {"status": "success", "timing": [{"name": "compile", "started_at": "2022-10-26T16:29:23.070975Z", "completed_at": "2022-10-26T16:29:23.075271Z"}, {"name": "execute", "started_at": "2022-10-26T16:29:23.075421Z", "completed_at": "2022-10-26T16:29:23.075426Z"}], "thread_id": "Thread-1", "execution_time": 0.004968166351318359, "adapter_response": {}, "message": null, "failures": null, "unique_id": "test.asana.unique_int_asana__task_first_modifier_task_id.59583c6dc2"}, {"status": "success", "timing": [{"name": "compile", "started_at": "2022-10-26T16:29:23.076304Z", "completed_at": "2022-10-26T16:29:23.093279Z"}, {"name": "execute", "started_at": "2022-10-26T16:29:23.093448Z", "completed_at": "2022-10-26T16:29:23.093453Z"}], "thread_id": "Thread-1", "execution_time": 0.017744064331054688, "adapter_response": {}, "message": null, "failures": null, "unique_id": "model.asana.asana__task"}, {"status": "success", "timing": [{"name": "compile", "started_at": "2022-10-26T16:29:23.094294Z", "completed_at": "2022-10-26T16:29:23.098149Z"}, {"name": "execute", "started_at": "2022-10-26T16:29:23.098291Z", "completed_at": "2022-10-26T16:29:23.098295Z"}], "thread_id": "Thread-1", "execution_time": 0.004503965377807617, "adapter_response": {}, "message": null, "failures": null, "unique_id": "test.asana.not_null_int_asana__task_open_length_task_id.23bb23b2e9"}, {"status": "success", "timing": [{"name": "compile", "started_at": "2022-10-26T16:29:23.098973Z", "completed_at": "2022-10-26T16:29:23.103554Z"}, {"name": "execute", "started_at": "2022-10-26T16:29:23.103707Z", "completed_at": "2022-10-26T16:29:23.103711Z"}], "thread_id": "Thread-1", "execution_time": 0.005217075347900391, "adapter_response": {}, "message": null, "failures": null, "unique_id": "test.asana.unique_int_asana__task_open_length_task_id.f26c49b044"}, {"status": "success", "timing": [{"name": "compile", "started_at": "2022-10-26T16:29:23.104429Z", "completed_at": "2022-10-26T16:29:25.412955Z"}, {"name": "execute", "started_at": "2022-10-26T16:29:25.413280Z", "completed_at": "2022-10-26T16:29:25.413299Z"}], "thread_id": "Thread-1", "execution_time": 2.309602975845337, "adapter_response": {}, "message": null, "failures": null, "unique_id": "model.asana.asana__daily_metrics"}, {"status": "success", "timing": [{"name": "compile", "started_at": "2022-10-26T16:29:25.415042Z", "completed_at": "2022-10-26T16:29:25.423994Z"}, {"name": "execute", "started_at": "2022-10-26T16:29:25.424210Z", "completed_at": "2022-10-26T16:29:25.424217Z"}], "thread_id": "Thread-1", "execution_time": 0.010158061981201172, "adapter_response": {}, "message": null, "failures": null, "unique_id": "model.asana.asana__tag"}, {"status": "success", "timing": [{"name": "compile", "started_at": "2022-10-26T16:29:25.433536Z", "completed_at": "2022-10-26T16:29:25.436845Z"}, {"name": "execute", "started_at": "2022-10-26T16:29:25.437014Z", "completed_at": "2022-10-26T16:29:25.437019Z"}], "thread_id": "Thread-1", "execution_time": 0.004056215286254883, "adapter_response": {}, "message": null, "failures": null, "unique_id": "test.asana.not_null_asana__task_task_id.6d36eb2cd0"}, {"status": "success", "timing": [{"name": "compile", "started_at": "2022-10-26T16:29:25.437848Z", "completed_at": "2022-10-26T16:29:25.440896Z"}, {"name": "execute", "started_at": "2022-10-26T16:29:25.441065Z", "completed_at": "2022-10-26T16:29:25.441070Z"}], "thread_id": "Thread-1", "execution_time": 0.0037877559661865234, "adapter_response": {}, "message": null, "failures": null, "unique_id": "test.asana.unique_asana__task_task_id.ebfe331df1"}, {"status": "success", "timing": [{"name": "compile", "started_at": "2022-10-26T16:29:25.441869Z", "completed_at": "2022-10-26T16:29:25.445504Z"}, {"name": "execute", "started_at": "2022-10-26T16:29:25.445652Z", "completed_at": "2022-10-26T16:29:25.445656Z"}], "thread_id": "Thread-1", "execution_time": 0.0043332576751708984, "adapter_response": {}, "message": null, "failures": null, "unique_id": "test.asana.not_null_asana__daily_metrics_date_day.363a2a09cf"}, {"status": "success", "timing": [{"name": "compile", "started_at": "2022-10-26T16:29:25.446397Z", "completed_at": "2022-10-26T16:29:25.449229Z"}, {"name": "execute", "started_at": "2022-10-26T16:29:25.449374Z", "completed_at": "2022-10-26T16:29:25.449378Z"}], "thread_id": "Thread-1", "execution_time": 0.0034971237182617188, "adapter_response": {}, "message": null, "failures": null, "unique_id": "test.asana.unique_asana__daily_metrics_date_day.e8d67f545d"}, {"status": "success", "timing": [{"name": "compile", "started_at": "2022-10-26T16:29:25.450110Z", "completed_at": "2022-10-26T16:29:25.452938Z"}, {"name": "execute", "started_at": "2022-10-26T16:29:25.453077Z", "completed_at": "2022-10-26T16:29:25.453081Z"}], "thread_id": "Thread-1", "execution_time": 0.0034890174865722656, "adapter_response": {}, "message": null, "failures": null, "unique_id": "test.asana.not_null_asana__tag_tag_id.593d626953"}, {"status": "success", "timing": [{"name": "compile", "started_at": "2022-10-26T16:29:25.453760Z", "completed_at": "2022-10-26T16:29:25.456257Z"}, {"name": "execute", "started_at": "2022-10-26T16:29:25.456398Z", "completed_at": "2022-10-26T16:29:25.456402Z"}], "thread_id": "Thread-1", "execution_time": 0.003117084503173828, "adapter_response": {}, "message": null, "failures": null, "unique_id": "test.asana.unique_asana__tag_tag_id.46c0d2510f"}, {"status": "success", "timing": [{"name": "compile", "started_at": "2022-10-26T16:29:25.457073Z", "completed_at": "2022-10-26T16:29:25.475139Z"}, {"name": "execute", "started_at": "2022-10-26T16:29:25.475276Z", "completed_at": "2022-10-26T16:29:25.475280Z"}], "thread_id": "Thread-1", "execution_time": 0.01867508888244629, "adapter_response": {}, "message": null, "failures": null, "unique_id": "model.asana.asana__project"}, {"status": "success", "timing": [{"name": "compile", "started_at": "2022-10-26T16:29:25.475945Z", "completed_at": "2022-10-26T16:29:25.480002Z"}, {"name": "execute", "started_at": "2022-10-26T16:29:25.480136Z", "completed_at": "2022-10-26T16:29:25.480140Z"}], "thread_id": "Thread-1", "execution_time": 0.004648923873901367, "adapter_response": {}, "message": null, "failures": null, "unique_id": "test.asana.not_null_int_asana__project_task_metrics_project_id.804fd1daf3"}, {"status": "success", "timing": [{"name": "compile", "started_at": "2022-10-26T16:29:25.480780Z", "completed_at": "2022-10-26T16:29:25.484822Z"}, {"name": "execute", "started_at": "2022-10-26T16:29:25.484957Z", "completed_at": "2022-10-26T16:29:25.484961Z"}], "thread_id": "Thread-1", "execution_time": 0.004635810852050781, "adapter_response": {}, "message": null, "failures": null, "unique_id": "test.asana.unique_int_asana__project_task_metrics_project_id.049cc9b8a6"}, {"status": "success", "timing": [{"name": "compile", "started_at": "2022-10-26T16:29:25.485608Z", "completed_at": "2022-10-26T16:29:25.496942Z"}, {"name": "execute", "started_at": "2022-10-26T16:29:25.497071Z", "completed_at": "2022-10-26T16:29:25.497075Z"}], "thread_id": "Thread-1", "execution_time": 0.011921882629394531, "adapter_response": {}, "message": null, "failures": null, "unique_id": "model.asana.asana__user"}, {"status": "success", "timing": [{"name": "compile", "started_at": "2022-10-26T16:29:25.497798Z", "completed_at": "2022-10-26T16:29:25.500957Z"}, {"name": "execute", "started_at": "2022-10-26T16:29:25.501088Z", "completed_at": "2022-10-26T16:29:25.501091Z"}], "thread_id": "Thread-1", "execution_time": 0.0037720203399658203, "adapter_response": {}, "message": null, "failures": null, "unique_id": "test.asana.not_null_int_asana__user_task_metrics_user_id.54eae7d721"}, {"status": "success", "timing": [{"name": "compile", "started_at": "2022-10-26T16:29:25.501734Z", "completed_at": "2022-10-26T16:29:25.506479Z"}, {"name": "execute", "started_at": "2022-10-26T16:29:25.506613Z", "completed_at": "2022-10-26T16:29:25.506617Z"}], "thread_id": "Thread-1", "execution_time": 0.005338907241821289, "adapter_response": {}, "message": null, "failures": null, "unique_id": "test.asana.unique_int_asana__user_task_metrics_user_id.06a6a270b8"}, {"status": "success", "timing": [{"name": "compile", "started_at": "2022-10-26T16:29:25.507256Z", "completed_at": "2022-10-26T16:29:25.509867Z"}, {"name": "execute", "started_at": "2022-10-26T16:29:25.509994Z", "completed_at": "2022-10-26T16:29:25.509998Z"}], "thread_id": "Thread-1", "execution_time": 0.003184795379638672, "adapter_response": {}, "message": null, "failures": null, "unique_id": "model.asana.asana__team"}, {"status": "success", "timing": [{"name": "compile", "started_at": "2022-10-26T16:29:25.510679Z", "completed_at": "2022-10-26T16:29:25.513040Z"}, {"name": "execute", "started_at": "2022-10-26T16:29:25.513163Z", "completed_at": "2022-10-26T16:29:25.513167Z"}], "thread_id": "Thread-1", "execution_time": 0.0029268264770507812, "adapter_response": {}, "message": null, "failures": null, "unique_id": "test.asana.not_null_asana__project_project_id.78420e1b45"}, {"status": "success", "timing": [{"name": "compile", "started_at": "2022-10-26T16:29:25.513785Z", "completed_at": "2022-10-26T16:29:25.516112Z"}, {"name": "execute", "started_at": "2022-10-26T16:29:25.516236Z", "completed_at": "2022-10-26T16:29:25.516240Z"}], "thread_id": "Thread-1", "execution_time": 0.0028939247131347656, "adapter_response": {}, "message": null, "failures": null, "unique_id": "test.asana.unique_asana__project_project_id.66a76364ef"}, {"status": "success", "timing": [{"name": "compile", "started_at": "2022-10-26T16:29:25.516861Z", "completed_at": "2022-10-26T16:29:25.519170Z"}, {"name": "execute", "started_at": "2022-10-26T16:29:25.519293Z", "completed_at": "2022-10-26T16:29:25.519297Z"}], "thread_id": "Thread-1", "execution_time": 0.002877950668334961, "adapter_response": {}, "message": null, "failures": null, "unique_id": "test.asana.not_null_asana__user_user_id.eb9cd93a43"}, {"status": "success", "timing": [{"name": "compile", "started_at": "2022-10-26T16:29:25.519933Z", "completed_at": "2022-10-26T16:29:25.522874Z"}, {"name": "execute", "started_at": "2022-10-26T16:29:25.523003Z", "completed_at": "2022-10-26T16:29:25.523006Z"}], "thread_id": "Thread-1", "execution_time": 0.003525972366333008, "adapter_response": {}, "message": null, "failures": null, "unique_id": "test.asana.unique_asana__user_user_id.3c4b63387e"}, {"status": "success", "timing": [{"name": "compile", "started_at": "2022-10-26T16:29:25.523635Z", "completed_at": "2022-10-26T16:29:25.525986Z"}, {"name": "execute", "started_at": "2022-10-26T16:29:25.526111Z", "completed_at": "2022-10-26T16:29:25.526115Z"}], "thread_id": "Thread-1", "execution_time": 0.0029211044311523438, "adapter_response": {}, "message": null, "failures": null, "unique_id": "test.asana.not_null_asana__team_team_id.cd6b6c88bf"}, {"status": "success", "timing": [{"name": "compile", "started_at": "2022-10-26T16:29:25.526732Z", "completed_at": "2022-10-26T16:29:25.529012Z"}, {"name": "execute", "started_at": "2022-10-26T16:29:25.529135Z", "completed_at": "2022-10-26T16:29:25.529138Z"}], "thread_id": "Thread-1", "execution_time": 0.0028438568115234375, "adapter_response": {}, "message": null, "failures": null, "unique_id": "test.asana.unique_asana__team_team_id.ada6b5e093"}], "elapsed_time": 9.388697862625122, "args": {"write_json": true, "use_colors": true, "printer_width": 80, "version_check": true, "partial_parse": true, "static_parser": true, "profiles_dir": "/Users/catherinefritz/.dbt", "send_anonymous_usage_stats": true, "event_buffer_size": 100000, "quiet": false, "no_print": false, "compile": true, "which": "generate", "rpc_method": "docs.generate", "indirect_selection": "eager"}}